{
  "name": "dialog-blinky",
  "version": "1.0.0",
  "title": "Dialog - Blinky",
  "description": "App to get started using DA1458x Bluetooth Low Energy (BLE) development kits from Dialog Semiconductor",
  "tags": [
	  {"label": "dialog", "type": "vendor"},
    {"label": "ble", "type": "comm"}],
  "libraries": [],
  "index-file": "index.html",
  "app-dir": "app",
  "uuid": "fe860e6e-d35e-4bd0-831a-7703ee2f8b01",
  "icon": "app-icon.png",
  "doc-url": "http://evothings.com/2.2/doc/examples/dialog-blinky.html"
}
